gaql/__init__.py
gaql/client/__init__.py
gaql/client/commands.py
gaql/lib/__init__.py
gaql/lib/click_decorators/__init__.py
gaql/lib/click_decorators/state.py
gaql/lib/functional.py
gaql/lib/google_clients/__init__.py
gaql/lib/google_clients/completion/__init__.py
gaql/lib/google_clients/completion/autocompletions.py
gaql/lib/google_clients/completion/google_completer.py
gaql/lib/google_clients/completion/trie.py
gaql/lib/google_clients/config.py
gaql/lib/google_clients/queries.py
gaql/lib/lexer.py
gaql/lib/output.py
gaql/lib/repl.py
gaql/lib/validation.py
gaql/main.py
gaql/tooling/autocomplete_generator.py
gaql/tools/__init__.py
gaql/tools/commands.py
gaql/tools/queries.py
gaql-1.15.0.dist-info/METADATA
gaql-1.15.0.dist-info/WHEEL
gaql-1.15.0.dist-info/entry_points.txt
gaql-1.15.0.dist-info/licenses/LICENSE
gaql-1.15.0.dist-info/RECORD
