Metadata-Version: 2.4
Name: gaql
Version: 1.15.0
Summary: A command line interface to the Google Ads Query Language (GAQL). Run with `gaql` or `gaql-tools`
License-File: LICENSE
Keywords: gaql,google-ads,cli
Author: Ben Ryves
Author-email: bryves@gmail.com
Requires-Python: >=3.9,<3.14
Classifier: Programming Language :: Python :: 3
Classifier: Programming Language :: Python :: 3.9
Classifier: Programming Language :: Python :: 3.10
Classifier: Programming Language :: Python :: 3.11
Classifier: Programming Language :: Python :: 3.12
Classifier: Programming Language :: Python :: 3.13
Requires-Dist: certifi (==2025.11.12)
Requires-Dist: click (>=8.0.3,<9.0.0)
Requires-Dist: google-ads (==28.4.0)
Requires-Dist: prompt_toolkit (>=3.0.22,<4.0.0)
Requires-Dist: pygments (>=2.10.0,<3.0.0)
Requires-Dist: toml (>=0.10.1,<0.11.0)
Project-URL: Homepage, https://github.com/getyourguide/gaql-cli
Project-URL: Repository, https://github.com/getyourguide/gaql-cli
